hydromace/__init__.py
hydromace/hessian_calculation.py
hydromace/interface.py
hydromace/model.py
hydromace/tools.py
hydromace/training.py
hydromace/training_tools.py
hydromace-0.2.dist-info/LICENSE
hydromace-0.2.dist-info/METADATA
hydromace-0.2.dist-info/WHEEL
hydromace-0.2.dist-info/top_level.txt
hydromace-0.2.dist-info/RECORD
