Metadata-Version: 2.1
Name: hydromace
Version: 0.2
Author-email: Rokas Elijošius <re344@cam.ac.uk>
License: MIT License
Requires-Python: >=3.10
License-File: LICENSE
Requires-Dist: mace-torch>=0.3.3
Requires-Dist: typer>=0.12
